Bohrmodel/__init__.py
Bohrmodel/atom.py
Bohrmodel/graficos.py
Bohrmodel/radios.py
Bohrmodel/transiciones.py
bohrmodel-0.1.0.dist-info/licenses/LICENSE
bohrmodel-0.1.0.dist-info/METADATA
bohrmodel-0.1.0.dist-info/WHEEL
bohrmodel-0.1.0.dist-info/top_level.txt
bohrmodel-0.1.0.dist-info/RECORD
