Metadata-Version: 2.4
Name: Bohrmodel
Version: 0.1.0
Summary: Cálculos del modelo de Bohr (Radios, Energía, Transiciones).
Author: Kevin Cruz Velandia
Author-email: Juan Esteban Neira Díaz <jueneirad@udistrital.edu.co>
Project-URL: homepage, https://github.com/XxyamzxX/-tomo_bohr.git
Classifier: Programming Language :: Python :: 3
Classifier: License :: OSI Approved :: MIT License
Classifier: Operating System :: OS Independent
Requires-Python: >=3.8
License-File: LICENSE
Requires-Dist: matplotlib
Requires-Dist: numpy
Dynamic: license-file
